{"seteffect":null,"weight":"melee","filename":"fire_cape","name":"Fire cape","type":"cape","level":3,"req_attack":0,"req_strength":0,"req_defence":3,"req_ranged":0,"req_magic":0,"req_prayer":0,"req_hitpoints":0,"url":"https://oldschool.runescape.wiki/images/5/54/Fire_cape.png","wiki":"https://oldschool.runescape.wiki/w/Fire_cape","height":1,"width":0,"atk_stab":1,"atk_slash":1,"atk_crush":1,"atk_magic":1,"atk_ranged":1,"def_stab":11,"def_slash":11,"def_crush":11,"def_magic":11,"def_ranged":11,"str_melee":4,"str_ranged":0,"str_magic":0,"str_prayer":2,"ZZ_positionX":25,"ZZ_positionY":17}