[{"filename":"animated_mithril_armour","name":"Animated Mithril Armour","wiki":"https://oldschool.runescape.wiki/w/Animated_Mithril_Armour","url":"https://oldschool.runescape.wiki/images/thumb/a/aa/Animated_Mithril_Armour.png/120px-Animated_Mithril_Armour.png","width":0.39867109634551495,"height":1,"cblevel":"92","size":"1x1","hitpoints":"80","attribute":null,"maxhit":"1","attackstyle":"Stab","attackspeed":"4","poisons":true,"poisonstooltip":"No","statsatk":"80","statsstr":"80","statsdef":"80","statsmagic":"1","statsranged":"1","aggressivestab":"0","aggressiveslash":"0","aggressivecrush":"0","aggressivemagic":"0","aggressiveranged":"0","defensestab":"50","defenseslash":"25","defensecrush":"19","defensemagic":"400","defenseranged":"400","stratt":null,"strstr":null,"strmagic":null,"strranged":null,"poison":true,"venom":true}]