[{"filename":"apmeken_(monster)","name":"Apmeken (monster)","wiki":"https://oldschool.runescape.wiki/w/Apmeken_(monster)","url":"https://oldschool.runescape.wiki/images/thumb/9/93/Apmeken_%28monster%29.png/110px-Apmeken_%28monster%29.png","width":0.3716216216216216,"height":1,"cblevel":"75","size":"1x1","hitpoints":"70","attribute":null,"maxhit":"8","attackstyle":"Magic, Slash","attackspeed":"4","poisons":true,"poisonstooltip":"No","statsatk":"30","statsstr":"40","statsdef":"60","statsmagic":"85","statsranged":"1","aggressivestab":"0","aggressiveslash":"0","aggressivecrush":"0","aggressivemagic":"0","aggressiveranged":"0","defensestab":"65","defenseslash":"65","defensecrush":"65","defensemagic":"50","defenseranged":"0","stratt":null,"strstr":null,"strmagic":null,"strranged":null,"poison":true,"venom":true}]