[{"filename":"bandosian_guard","name":"Bandosian guard","wiki":"https://oldschool.runescape.wiki/w/Bandosian_guard","url":"https://oldschool.runescape.wiki/images/thumb/9/9e/Bandosian_guard.png/250px-Bandosian_guard.png","width":0.8620689655172413,"height":1,"cblevel":"125","size":"1x1","hitpoints":"130","attribute":null,"maxhit":"1","attackstyle":"Stab","attackspeed":"5","poisons":true,"poisonstooltip":"No","statsatk":"110","statsstr":"115","statsdef":"80","statsmagic":"1","statsranged":"1","aggressivestab":"0","aggressiveslash":"0","aggressivecrush":"0","aggressivemagic":"0","aggressiveranged":"0","defensestab":"12","defenseslash":"14","defensecrush":"13","defensemagic":"5","defenseranged":"13","stratt":null,"strstr":null,"strmagic":null,"strranged":null,"poison":true,"venom":true}]