[{"filename":"mother","name":"Mother","wiki":"https://oldschool.runescape.wiki/w/Mother","url":"https://oldschool.runescape.wiki/images/thumb/8/87/Mother.png/180px-Mother.png","width":0.5157593123209169,"height":1,"cblevel":"198","size":"3x3","hitpoints":"235","attribute":null,"maxhit":"1","attackstyle":"Ranged, Crush","attackspeed":"4","poisons":true,"poisonstooltip":"No","statsatk":"150","statsstr":"150","statsdef":"170","statsmagic":"60","statsranged":"105","aggressivestab":"0","aggressiveslash":"0","aggressivecrush":"0","aggressivemagic":"0","aggressiveranged":"0","defensestab":"0","defenseslash":"0","defensecrush":"0","defensemagic":"200","defenseranged":"0","stratt":null,"strstr":null,"strmagic":null,"strranged":null,"poison":true,"venom":true}]