[{"filename":"third_age_warrior","name":"Third Age Warrior","wiki":"https://oldschool.runescape.wiki/w/Third_Age_Warrior","url":"https://oldschool.runescape.wiki/images/thumb/6/66/Third_Age_Warrior.png/180px-Third_Age_Warrior.png","width":0.5142857142857142,"height":1,"cblevel":"83","size":"1x1","hitpoints":"40","attribute":null,"maxhit":"1","attackstyle":"Slash","attackspeed":"5","poisons":true,"poisonstooltip":"No","statsatk":"90","statsstr":"75","statsdef":"80","statsmagic":"1","statsranged":"1","aggressivestab":"0","aggressiveslash":"0","aggressivecrush":"0","aggressivemagic":"0","aggressiveranged":"0","defensestab":"96","defenseslash":"108","defensecrush":"113","defensemagic":"-4","defenseranged":"97","stratt":null,"strstr":null,"strmagic":null,"strranged":null,"poison":true,"venom":true}]